SimpleSEDML/__init__.py
SimpleSEDML/constants.py
SimpleSEDML/executor.py
SimpleSEDML/model.py
SimpleSEDML/model_information.py
SimpleSEDML/multiple_model_parameter_scan.py
SimpleSEDML/multiple_model_simple_sedml.py
SimpleSEDML/multiple_model_time_course.py
SimpleSEDML/omex_maker.py
SimpleSEDML/plot.py
SimpleSEDML/report.py
SimpleSEDML/simple_sedml.py
SimpleSEDML/simulation.py
SimpleSEDML/single_model_parameter_scan.py
SimpleSEDML/single_model_time_course.py
SimpleSEDML/task.py
SimpleSEDML/utils.py
SimpleSEDML/variable_collection.py
simplesedml-0.2.0.dist-info/licenses/LICENSE
tests/test__init__.py
tests/test_executor.py
tests/test_model.py
tests/test_model_information.py
tests/test_multiple_model_parameter_scan.py
tests/test_multiple_model_time_course.py
tests/test_omex_maker.py
tests/test_plot.py
tests/test_report.py
tests/test_simple_sedml.py
tests/test_simulation.py
tests/test_single_model_parameter_scan.py
tests/test_single_model_time_course.py
tests/test_task.py
tests/test_utils.py
tests/test_variable_collection.py
simplesedml-0.2.0.dist-info/METADATA
simplesedml-0.2.0.dist-info/WHEEL
simplesedml-0.2.0.dist-info/top_level.txt
simplesedml-0.2.0.dist-info/RECORD
