Metadata-Version: 2.4
Name: SimpleSEDML
Version: 0.2.0
Summary: Python Subnet Discovery for Systems Biology
Author-email: Joseph Hellerstein <joseph.hellerstein@gmail.com>, Herbert S Sauro <hsauro@uw.edu>
License: MIT License
Project-URL: Homepage, https://github.com/sys-bio/SimpleSEDML
Requires-Python: >=3.6
License-File: LICENSE
Requires-Dist: biomodels_qc
Requires-Dist: biosimulators_utils
Requires-Dist: numpy
Requires-Dist: build
Requires-Dist: coverage
Requires-Dist: jupyterlab
Requires-Dist: matplotlib
Requires-Dist: nose2
Requires-Dist: pandas
Requires-Dist: phrasedml
Requires-Dist: pip
Requires-Dist: python-libsbml
Requires-Dist: requests
Requires-Dist: tabulate
Requires-Dist: tellurium
Requires-Dist: twine
Requires-Dist: urllib3
Dynamic: license-file
